haneen/__init__.py
haneen/core.py
haneen-0.1.0.dist-info/METADATA
haneen-0.1.0.dist-info/WHEEL
haneen-0.1.0.dist-info/top_level.txt
haneen-0.1.0.dist-info/RECORD
