Metadata-Version: 2.4
Name: Haneen
Version: 0.1.0
Summary: A simple package with dp and graph functions
Author-email: Ahmed Hafez <your_email@example.com>
License: MIT
Project-URL: Homepage, https://github.com/yourusername/Haneen
Requires-Python: >=3.8
